common/__init__.py
common/common_behav.py
common/common_device.py
common/common_dio.py
common/common_ephys.py
common/common_filter.py
common/common_interval.py
common/common_lab.py
common/common_nwbfile.py
common/common_region.py
common/common_sensors.py
common/common_session.py
common/common_spikesorting.py
common/common_subject.py
common/common_task.py
common/dj_helper_fn.py
common/nwb_helper_fn.py
common/populate_all_common.py
common/signal_processing.py
data_import/__init__.py
data_import/insert_sessions.py
data_import/storage_dirs.py
lock/__init__.py
lock/file_lock.py
ndx_franklab_novela/__init__.py
ndx_franklab_novela/associated_files.py
ndx_franklab_novela/camera_device.py
ndx_franklab_novela/data_acq_device.py
ndx_franklab_novela/header_device.py
ndx_franklab_novela/nwb_electrode_group.py
ndx_franklab_novela/nwb_image_series.py
ndx_franklab_novela/probe.py
nwb_datajoint/__init__.py
nwb_datajoint/common/__init__.py
nwb_datajoint/common/common_behav.py
nwb_datajoint/common/common_device.py
nwb_datajoint/common/common_dio.py
nwb_datajoint/common/common_ephys.py
nwb_datajoint/common/common_filter.py
nwb_datajoint/common/common_interval.py
nwb_datajoint/common/common_lab.py
nwb_datajoint/common/common_nwbfile.py
nwb_datajoint/common/common_region.py
nwb_datajoint/common/common_sensors.py
nwb_datajoint/common/common_session.py
nwb_datajoint/common/common_spikesorting.py
nwb_datajoint/common/common_subject.py
nwb_datajoint/common/common_task.py
nwb_datajoint/common/dj_helper_fn.py
nwb_datajoint/common/nwb_helper_fn.py
nwb_datajoint/common/populate_all_common.py
nwb_datajoint/common/signal_processing.py
nwb_datajoint/data_import/__init__.py
nwb_datajoint/data_import/insert_sessions.py
nwb_datajoint/data_import/storage_dirs.py
nwb_datajoint/lock/__init__.py
nwb_datajoint/lock/file_lock.py
nwb_datajoint/tests/__init__.py
nwb_datajoint/tests/_temporarydirectory.py
nwb_datajoint/tests/conftest.py
nwb_datajoint/tests/test_1.py
nwb_datajoint/tests/data_import/__init__.py
nwb_datajoint-0.2.6.dist-info/LICENSE
nwb_datajoint-0.2.6.dist-info/METADATA
nwb_datajoint-0.2.6.dist-info/WHEEL
nwb_datajoint-0.2.6.dist-info/top_level.txt
nwb_datajoint-0.2.6.dist-info/RECORD
