Metadata-Version: 2.1
Name: nwb-datajoint
Version: 0.2.6
Summary: Neuroscience data pipeline for reproducible research used by Loren Frank Lab, UCSF
Home-page: https://github.com/LorenFrankLab/nwb_datajoint
Author: Loren Frank, Eric Denovellis, Kyu Hyun Lee, Ryan Ly
Author-email: loren@phy.ucsf.edu
License: UNKNOWN
Project-URL: Bug Tracker, https://github.com/LorenFrankLab/nwb_datajoint/issues
Platform: UNKNOWN
Classifier: Programming Language :: Python :: 3
Classifier: License :: OSI Approved :: MIT License
Classifier: Operating System :: OS Independent
Requires-Python: >=3.8
